vshinet/HINet-GoPro.pth
vshinet/HINet-REDS.pth
vshinet/HINet-Rain13k.pth
vshinet/HINet-SIDD-1x.pth
vshinet/__init__.py
vshinet/__main__.py
vshinet/hinet_arch.py
vshinet-1.0.0.dist-info/LICENSE
vshinet-1.0.0.dist-info/METADATA
vshinet-1.0.0.dist-info/WHEEL
vshinet-1.0.0.dist-info/top_level.txt
vshinet-1.0.0.dist-info/RECORD
