Metadata-Version: 2.1
Name: vshinet
Version: 1.0.0
Summary: HINet function for VapourSynth
Home-page: https://github.com/HolyWu/vs-hinet
Author: HolyWu
License: UNKNOWN
Platform: UNKNOWN
Classifier: License :: OSI Approved :: MIT License
Classifier: Operating System :: OS Independent
Classifier: Programming Language :: Python :: 3
Classifier: Programming Language :: Python :: 3 :: Only
Classifier: Topic :: Multimedia :: Video
Requires-Python: >=3.6
License-File: LICENSE
Requires-Dist: numpy
Requires-Dist: requests
Requires-Dist: torch (>=1.9.0)
Requires-Dist: tqdm
Requires-Dist: VapourSynth (>=55)
